Metadata-Version: 2.1
Name: trujillo-dynamics-package
Version: 0.1.0
Summary: Paquete que tiene como proposito el brindar clases de permitan realizar una conexión con data entities de Dynamics 365 Finance and Operations
Home-page: UNKNOWN
Author: Fernando Colque
Author-email: fernando.colque@terranovatrading.com.pe
License: MIT
Platform: UNKNOWN
